{
    "id": 3,
    "name": "Tecumseh Titty Twisters",
    "logo": "team3logo.png",
    "players": [
        {
            "name": "Landon Rincer",
            "birth year": "2004",
            "position": "Defenseman",
            "number": "05"
        },
        {
            "name": "Jonathan Sexsmith",
            "birth year": "2004",
            "position": "Defenseman",
            "number": "00"
        },
        {
            "name": "Spencer Zazer",
            "birth year": "2002",
            "position": "Forward",
            "number": "00"
        },
        {
            "name": "Curtis Jackson",
            "birth year": "2001",
            "position": "Forward",
            "number": "00"
        },
        {
            "name": "Jonas Columbus",
            "birth year": "2004",
            "position": "Forward",
            "number": "00"
        },
        {
            "name": "Andrew",
            "birth year": "2004",
            "position": "Forward/Defenseman",
            "number": "00"
        },
        {
            "name": "Evan Fenech",
            "birth year": "2006",
            "position": "Defenseman",
            "number": "00"
        },
        {
            "name": "Ryan Sterling",
            "birth year": "2001",
            "position": "Forward/Defenseman",
            "number": "00"
        },
        {
            "name": "Kyle Bleau",
            "birth year": "2004",
            "position": "Forward",
            "number": "00"
        },
        {
            "name": "Liam Prince",
            "birth year": "2003",
            "position": "Forward",
            "number": "00"
        },
        {
            "name": "Max Sieberer",
            "birth year": "2000",
            "position": "Forward",
            "number": "00"
        },
        {
            "name": "Tyler fuhr",
            "birth year": "2004",
            "position": "Forward",
            "number": "00"
        },
        {
            "name": "Michael Rohrer",
            "birth year": "2003",
            "position": "Defenseman",
            "number": "00"
        },
        {
            "name": "Kaleb Simpson",
            "birth year": "2004",
            "position": "Forward",
            "number": "00"
        },
        {
            "name": "Tyler Burton",
            "birth year": "2006",
            "position": "Goalie",
            "number": "00"
        },
        {
            "name": "Jake Gaudario",
            "birth year": "2004",
            "position": "Forward",
            "number": "00"
        }
    ]
}